cbr_athena/__init__.py
cbr_athena/athena__fastapi/FastAPI_Athena.py
cbr_athena/athena__fastapi/__init__.py
cbr_athena/athena__fastapi/llms/LLMs__Fast_API.py
cbr_athena/athena__fastapi/llms/__init__.py
cbr_athena/athena__fastapi/llms/routes/Routes__Chat.py
cbr_athena/athena__fastapi/middleware/__init__.py
cbr_athena/athena__fastapi/middleware/add_logging.py
cbr_athena/athena__fastapi/odin/FastApi_Header_Auth.py
cbr_athena/athena__fastapi/odin/Odin__FastAPI.py
cbr_athena/athena__fastapi/odin/TestCase__Odin__FastAPI.py
cbr_athena/athena__fastapi/odin/__init__.py
cbr_athena/athena__fastapi/odin/api/Odin__FastAPI__API.py
cbr_athena/athena__fastapi/odin/api/__init__.py
cbr_athena/athena__fastapi/odin/api/routes/Routes__Odin__Info.py
cbr_athena/athena__fastapi/odin/api/routes/Routes__Security.py
cbr_athena/athena__fastapi/odin/api/routes/__init__.py
cbr_athena/athena__fastapi/odin/chat/Odin__Execute__Workflow.py
cbr_athena/athena__fastapi/odin/chat/Odin__FastAPI__Chat.py
cbr_athena/athena__fastapi/odin/chat/Odin__LLM_Prompt.py
cbr_athena/athena__fastapi/odin/chat/Odin__LLM_Prompt__Workflow.py
cbr_athena/athena__fastapi/odin/chat/__init__.py
cbr_athena/athena__fastapi/odin/chat/routes/Routes__LLMs.py
cbr_athena/athena__fastapi/odin/chat/routes/__init__.py
cbr_athena/athena__fastapi/routes/Fast_API_Route.py
cbr_athena/athena__fastapi/routes/Routes__Config.py
cbr_athena/athena__fastapi/routes/Routes__Dev.py
cbr_athena/athena__fastapi/routes/Routes__Logging.py
cbr_athena/athena__fastapi/routes/Routes__Ollama.py
cbr_athena/athena__fastapi/routes/Routes__OpenAI.py
cbr_athena/athena__fastapi/routes/__init__.py
cbr_athena/athena__fastapi/routes_paths.py
cbr_athena/aws/__init__.py
cbr_athena/aws/dynamo_db/DyDB__CBR_Chat_Threads.py
cbr_athena/aws/dynamo_db/DyDB__CBR_Logging.py
cbr_athena/aws/dynamo_db/DyDB__CBR_Requests.py
cbr_athena/aws/dynamo_db/DyDB__CBR_Workflows.py
cbr_athena/aws/dynamo_db/__init__.py
cbr_athena/config/CBR__Config__Athena.py
cbr_athena/config/__init__.py
cbr_athena-0.57.17.dist-info/LICENSE
cbr_athena-0.57.17.dist-info/METADATA
cbr_athena-0.57.17.dist-info/WHEEL
cbr_athena-0.57.17.dist-info/RECORD
