Metadata-Version: 2.3
Name: cbr-athena
Version: 0.57.17
Summary: CBR Athena
License: MIT
Author: Dinis Cruz
Author-email: dinis.cruz@owasp.org
Requires-Python: >=3.11,<4.0
Classifier: License :: OSI Approved :: MIT License
Classifier: Programming Language :: Python :: 3
Classifier: Programming Language :: Python :: 3.11
Classifier: Programming Language :: Python :: 3.12
Classifier: Programming Language :: Python :: 3.13
Requires-Dist: boto3
Requires-Dist: cbr-shared
Requires-Dist: cbr-static
Requires-Dist: cbr-user-data
Requires-Dist: cbr-user-session
Requires-Dist: fastapi
Requires-Dist: mangum
Requires-Dist: numpy
Requires-Dist: openai
Requires-Dist: osbot-aws
Requires-Dist: osbot-fast_api
Requires-Dist: osbot-github
Requires-Dist: osbot-local-stack
Requires-Dist: osbot-utils
Requires-Dist: pyjwt
Requires-Dist: uvicorn
Project-URL: Homepage, https://github.com/the-cyber-boardroom/cbr-athena
